src/__init__.py
src/main.py
CleverPIP-0.1.3.dist-info/LICENSE
CleverPIP-0.1.3.dist-info/METADATA
CleverPIP-0.1.3.dist-info/WHEEL
CleverPIP-0.1.3.dist-info/entry_points.txt
CleverPIP-0.1.3.dist-info/top_level.txt
CleverPIP-0.1.3.dist-info/RECORD
