Metadata-Version: 2.1
Name: CleverPIP
Version: 0.1.3
Summary: A simple PIP tool to automatically upgrade packages to your liking.
Home-page: https://github.com/L1Lbg/CleverPIP
Download-URL: https://github.com/L1Lbg/CleverPIP/archive/refs/tags/0.1.0.tar.gz
Author: Luca
Author-email: luca.baeyens@icloud.com
Classifier: Programming Language :: Python :: 3
Classifier: License :: OSI Approved :: MIT License
Classifier: Operating System :: OS Independent
Requires-Python: >=3.6
License-File: LICENSE
Requires-Dist: packaging
